noise_robust_differentiator/__init__.py
noise_robust_differentiator/derivatives.py
noise_robust_differentiator-0.0.2.dist-info/LICENSE
noise_robust_differentiator-0.0.2.dist-info/METADATA
noise_robust_differentiator-0.0.2.dist-info/WHEEL
noise_robust_differentiator-0.0.2.dist-info/top_level.txt
noise_robust_differentiator-0.0.2.dist-info/RECORD
